web_scraper/__init__.py
web_scraper/find_links_by_extension.py
web_scraper/get_links_directly.py
web_scraper/get_links_using_Google_search.py
web_scraper-1.0.dist-info/DESCRIPTION.rst
web_scraper-1.0.dist-info/METADATA
web_scraper-1.0.dist-info/RECORD
web_scraper-1.0.dist-info/WHEEL
web_scraper-1.0.dist-info/metadata.json
web_scraper-1.0.dist-info/top_level.txt
