Metadata-Version: 2.0
Name: web-scraper
Version: 1.0
Summary: A package for getting data from the intenet
Home-page: https://github.com/vvaezian/Web-Scraper
Author: Vahid Vaezian
Author-email: vahid.vaezian@gmail.com
License: UNKNOWN
Platform: UNKNOWN
Classifier: Programming Language :: Python :: 2.7
Classifier: License :: OSI Approved :: MIT License
Classifier: Operating System :: OS Independent
